{"assets/images/Diskon.png":["assets/images/Diskon.png"],"assets/images/Headlamp.png":["assets/images/Headlamp.png"],"assets/images/Hydropack.png":["assets/images/Hydropack.png"],"assets/images/Mountain.png":["assets/images/Mountain.png"],"assets/images/Outdoor.png":["assets/images/Outdoor.png"],"assets/images/Sarungtangan.png":["assets/images/Sarungtangan.png"],"assets/images/Sepatu.png":["assets/images/Sepatu.png"],"assets/images/Sepatu2.png":["assets/images/Sepatu2.png"],"assets/images/Sepatu3.png":["assets/images/Sepatu3.png"],"assets/images/Sepatu5.png":["assets/images/Sepatu5.png"],"assets/images/Tenda.png":["assets/images/Tenda.png"],"assets/images/Tenda2.png":["assets/images/Tenda2.png"],"assets/images/background.png":["assets/images/background.png"],"assets/images/background1.png":["assets/images/background1.png"],"assets/images/backgroundcarrier.png":["assets/images/backgroundcarrier.png"],"assets/images/backgroundheadlamp.png":["assets/images/backgroundheadlamp.png"],"assets/images/backgroundhydropack.png":["assets/images/backgroundhydropack.png"],"assets/images/backgroundjacket.jpg":["assets/images/backgroundjacket.jpg"],"assets/images/backgroundkomporportable.png":["assets/images/backgroundkomporportable.png"],"assets/images/backgroundsarungtangan.png":["assets/images/backgroundsarungtangan.png"],"assets/images/backgroundsepatu.png":["assets/images/backgroundsepatu.png"],"assets/images/backgroundsleepingbag.png":["assets/images/backgroundsleepingbag.png"],"assets/images/backgroundtenda.jpg":["assets/images/backgroundtenda.jpg"],"assets/images/backgroundtrackingpole.png":["assets/images/backgroundtrackingpole.png"],"assets/images/carrier.png":["assets/images/carrier.png"],"assets/images/carrier2.png":["assets/images/carrier2.png"],"assets/images/carrier60L.png":["assets/images/carrier60L.png"],"assets/images/fais.png":["assets/images/fais.png"],"assets/images/jacket1.png":["assets/images/jacket1.png"],"assets/images/jacket2.png":["assets/images/jacket2.png"],"assets/images/jacket3.png":["assets/images/jacket3.png"],"assets/images/komporportable.png":["assets/images/komporportable.png"],"assets/images/logo.png":["assets/images/logo.png"],"assets/images/sleepingbag.png":["assets/images/sleepingbag.png"],"assets/images/trackingpole1.png":["assets/images/trackingpole1.png"],"packages/cupertino_icons/assets/CupertinoIcons.ttf":["packages/cupertino_icons/assets/CupertinoIcons.ttf"],"packages/getwidget/icons/dribble.png":["packages/getwidget/icons/dribble.png"],"packages/getwidget/icons/facebook.png":["packages/getwidget/icons/facebook.png"],"packages/getwidget/icons/google.png":["packages/getwidget/icons/google.png"],"packages/getwidget/icons/line.png":["packages/getwidget/icons/line.png"],"packages/getwidget/icons/linkedin.png":["packages/getwidget/icons/linkedin.png"],"packages/getwidget/icons/pinterest.png":["packages/getwidget/icons/pinterest.png"],"packages/getwidget/icons/slack.png":["packages/getwidget/icons/slack.png"],"packages/getwidget/icons/twitter.png":["packages/getwidget/icons/twitter.png"],"packages/getwidget/icons/wechat.png":["packages/getwidget/icons/wechat.png"],"packages/getwidget/icons/whatsapp.png":["packages/getwidget/icons/whatsapp.png"],"packages/getwidget/icons/youtube.png":["packages/getwidget/icons/youtube.png"]}